gov_uk_dashboards/__init__.py
gov_uk_dashboards/colours.py
gov_uk_dashboards/constants.py
gov_uk_dashboards/log_kpi.py
gov_uk_dashboards/symbols.py
gov_uk_dashboards/template.html
gov_uk_dashboards/template.py
gov_uk_dashboards/assets/__init__.py
gov_uk_dashboards/assets/attach-event-to-dash.js
gov_uk_dashboards/assets/custom_map_style_functions.js
gov_uk_dashboards/assets/dashboard.css
gov_uk_dashboards/assets/download-map.js
gov_uk_dashboards/assets/get_assets_folder.py
gov_uk_dashboards/assets/govuk-frontend-3.14.0.min.js
gov_uk_dashboards/assets/index.html
gov_uk_dashboards/assets/mobile-nav.js
gov_uk_dashboards/assets/register_maps
gov_uk_dashboards/assets/scripts.js
gov_uk_dashboards/assets/fonts/bold-affa96571d-v2.woff
gov_uk_dashboards/assets/fonts/bold-b542beb274-v2.woff2
gov_uk_dashboards/assets/fonts/light-94a07e06a1-v2.woff2
gov_uk_dashboards/assets/fonts/light-f591b13f7d-v2.woff
gov_uk_dashboards/assets/images/DLUHC_WHITE_Master_AW_sm.png
gov_uk_dashboards/assets/images/MHCLG-favicon.png
gov_uk_dashboards/assets/images/MHCLG_favicon.png
gov_uk_dashboards/assets/images/dcms_coatofarms.png
gov_uk_dashboards/assets/images/dluhc_favicon.ico
gov_uk_dashboards/assets/images/gov_favicon.ico
gov_uk_dashboards/assets/images/govuk-crest.svg
gov_uk_dashboards/assets/images/hm-government-logo.png
gov_uk_dashboards/assets/images/mhclg_coat_of_arms.png
gov_uk_dashboards/assets/images/mhclg_white_no_background.png
gov_uk_dashboards/assets/images/oflog/MedianAbsolute.png
gov_uk_dashboards/assets/images/oflog/how_to_1_selecting_data.png
gov_uk_dashboards/assets/images/oflog/how_to_2_viewing_tabs.png
gov_uk_dashboards/assets/images/oflog/how_to_3_viewing_charts.png
gov_uk_dashboards/assets/images/oflog/how_to_4_viewing_trends.png
gov_uk_dashboards/assets/images/oflog/how_to_5_viewing_tables.png
gov_uk_dashboards/assets/topojson/usa_110m.json
gov_uk_dashboards/assets/topojson/world_110m.json
gov_uk_dashboards/components/__init__.py
gov_uk_dashboards-26.21.2.dist-info/licenses/LICENSE
gov_uk_dashboards-26.21.2.dist-info/METADATA
gov_uk_dashboards-26.21.2.dist-info/WHEEL
gov_uk_dashboards-26.21.2.dist-info/top_level.txt
gov_uk_dashboards-26.21.2.dist-info/RECORD
