Metadata-Version: 2.4
Name: gov_uk_dashboards
Version: 26.21.2
Summary: Provides access to functionality common to creating a data dashboard.
Author: Department for Levelling Up, Housing and Communities
License-File: LICENSE
Requires-Dist: setuptools<81.0,>=59.8
Requires-Dist: dash~=3.0
Requires-Dist: numpy>=2.3.2
Requires-Dist: dash_bootstrap_components~=2.0.3
Requires-Dist: plotly<6.6,>=6.2
Requires-Dist: flask-basicauth~=0.2.0
Dynamic: author
Dynamic: description
Dynamic: description-content-type
Dynamic: license-file
Dynamic: requires-dist
Dynamic: summary
